easyplot_toolbox/__init__.py
easyplot_toolbox/easyplot.py
easyplot_toolbox-2.0.2.dist-info/license.md
easyplot_toolbox-2.0.2.dist-info/METADATA
easyplot_toolbox-2.0.2.dist-info/WHEEL
easyplot_toolbox-2.0.2.dist-info/RECORD
