Metadata-Version: 2.1
Name: easyplot-toolbox
Version: 2.0.2
Summary: 
Author: wmpjrufg
Author-email: wanderlei_junior@ufcat.edu.br
Requires-Python: >3.8
Classifier: Programming Language :: Python :: 3
Classifier: Programming Language :: Python :: 3.9
Classifier: Programming Language :: Python :: 3.10
Classifier: Programming Language :: Python :: 3.11
Classifier: Programming Language :: Python :: 3.12
Requires-Dist: joypy (>0.2.6)
Requires-Dist: matplotlib (>3.8.4)
Requires-Dist: numpy (>1.23)
Requires-Dist: pandas (>2.2.2)
Requires-Dist: seaborn (>0.13.2)
Requires-Dist: squarify (>0.4.3)
